mosaik_components/pv/__init__.py
mosaik_components/pv/pvpanel.py
mosaik_components/pv/pvsimulator.py
mosaik_pv-1.2.2.dist-info/METADATA
mosaik_pv-1.2.2.dist-info/WHEEL
mosaik_pv-1.2.2.dist-info/licenses/AUTHORS.rst
mosaik_pv-1.2.2.dist-info/licenses/LICENSE.txt
mosaik_pv-1.2.2.dist-info/RECORD
