Metadata-Version: 2.4
Name: mosaik-pv
Version: 1.2.2
Summary: PV Simulator for Mosaik
License-Expression: CC-BY-3.0
License-File: AUTHORS.rst
License-File: LICENSE.txt
Author: Cornelius Steinbrink
Author-email: mosaik@offis.de
Requires-Python: >=3.9
Classifier: Programming Language :: Python :: 3
Classifier: Programming Language :: Python :: 3.9
Classifier: Programming Language :: Python :: 3.10
Classifier: Programming Language :: Python :: 3.11
Classifier: Programming Language :: Python :: 3.12
Classifier: Programming Language :: Python :: 3.13
Classifier: Programming Language :: Python :: 3.14
Requires-Dist: arrow (>=1.3.0)
Requires-Dist: mosaik-api-v3 (>=3.0.7)
Requires-Dist: numpy (>=1.26.1)
Requires-Dist: tqdm (>=4.66.1)
